anti_useragent/__init__.py
anti_useragent/exceptions.py
anti_useragent/settings/__init__.py
anti_useragent/settings/default_settings.py
anti_useragent/useragent/__init__.py
anti_useragent/useragent/ua.py
anti_useragent/useragent/browser/__init__.py
anti_useragent/useragent/browser/baidu.py
anti_useragent/useragent/browser/chrome.py
anti_useragent/useragent/browser/firefox.py
anti_useragent/useragent/browser/opera.py
anti_useragent/useragent/browser/uc.py
anti_useragent/useragent/browser/wechat.py
anti_useragent/utils/__init__.py
anti_useragent/utils/cipers.py
anti_useragent/utils/log.py
anti_useragent/utils/misc.py
anti_useragent/utils/scrapy_contextfactory.py
anti_useragent-1.0.10.dist-info/LICENSE
anti_useragent-1.0.10.dist-info/METADATA
anti_useragent-1.0.10.dist-info/WHEEL
anti_useragent-1.0.10.dist-info/top_level.txt
anti_useragent-1.0.10.dist-info/RECORD
