Metadata-Version: 2.1
Name: anti_useragent
Version: 1.0.10
Summary: fake pc or app browser useragent, anti useragent, and other awesome tools
Home-page: https://github.com/ihandmine/anti-useragent
Author: handmine
Author-email: handmine@outlook.com
License: MIT
Keywords: user,agent,user agent,useragent,fake,fake useragent,fake user agent,anti,anti useragent
Platform: UNKNOWN
Classifier: License :: OSI Approved :: MIT License
Classifier: Programming Language :: Python
Classifier: Intended Audience :: Developers
Classifier: Operating System :: OS Independent
Requires-Python: >=3.7.0
